testcase_maker/__init__.py
testcase_maker/constants.py
testcase_maker/executor.py
testcase_maker/executor_manager.py
testcase_maker/generator.py
testcase_maker/resolver.py
testcase_maker/subtask.py
testcase_maker/utils.py
testcase_maker/value.py
testcase_maker/executors/__init__.py
testcase_maker/executors/cpp.py
testcase_maker/executors/java.py
testcase_maker/executors/python.py
testcase_maker/values/__init__.py
testcase_maker/values/constant.py
testcase_maker/values/loop_value.py
testcase_maker/values/named_value.py
testcase_maker/values/random_choice.py
testcase_maker/values/random_int.py
testcase_maker/values/random_sample.py
testcase_maker/values/range.py
testcase_maker/values/value_group.py
testcase_maker/values/value_ref.py
testcase_maker-0.3.0.post0.dist-info/LICENSE
testcase_maker-0.3.0.post0.dist-info/METADATA
testcase_maker-0.3.0.post0.dist-info/WHEEL
testcase_maker-0.3.0.post0.dist-info/top_level.txt
testcase_maker-0.3.0.post0.dist-info/RECORD
